Chemical_Descriptors/__init__.py
Chemical_Descriptors-0.0.1.dist-info/LICENCE.txt
Chemical_Descriptors-0.0.1.dist-info/METADATA
Chemical_Descriptors-0.0.1.dist-info/WHEEL
Chemical_Descriptors-0.0.1.dist-info/top_level.txt
Chemical_Descriptors-0.0.1.dist-info/RECORD
