Metadata-Version: 2.1
Name: Chemical_Descriptors
Version: 0.0.1
Summary: Chemical descriptors is a powerful Python package facilitating calculation of fingerprints for CSV files
Home-page: https://github.com/AhmedAlhilal14/chemical-descriptors.git
Author: Ahmed Alhilal
Author-email: aalhilal@udel.edu
License: MIT
Keywords: Cheminformatics,Molecular Descriptors,Fingerprints,RDKit,Mordred,Padelpy
Classifier: Development Status :: 5 - Production/Stable
Classifier: Intended Audience :: Education
Classifier: Operating System :: Microsoft :: Windows :: Windows 10
Classifier: License :: OSI Approved :: MIT License
Classifier: Programming Language :: Python :: 3
License-File: LICENCE.txt
Requires-Dist: rdkit
Requires-Dist: mordred
Requires-Dist: pandas
Requires-Dist: numpy
Requires-Dist: matplotlib
Requires-Dist: padelpy
Requires-Dist: molfeat
Requires-Dist: matplotlib-venn
